{
  "material": {
    "height": 1373.9205090447488,
    "width": 3592.299236237289
  },
  "orders": [
    {
      "part": {
        "height": 141.5380632328453,
        "id": 3370942770122409219,
        "width": 399.49665964185965
      },
      "quantity": 3
    },
    {
      "part": {
        "height": 244.73212194453538,
        "id": 11684695510539124230,
        "width": 103.65531279835278
      },
      "quantity": 7
    },
    {
      "part": {
        "height": 259.90285295593134,
        "id": 2695210518275375233,
        "width": 312.0070818463
      },
      "quantity": 7
    },
    {
      "part": {
        "height": 214.2656674595121,
        "id": 5292332997483355749,
        "width": 287.58595422625496
      },
      "quantity": 2
    },
    {
      "part": {
        "height": 65.29007077227588,
        "id": 4520298553738860474,
        "width": 105.18899412417082
      },
      "quantity": 1
    }
  ]
}